Metadata-Version: 2.1
Name: downdot
Version: 0.0.1
Summary: A CLI for installing with pipo  and conda
Home-page: https://villiasdev.github.io
Author: Villias
